brandaniethical/__init__.py
brandaniethical/brandaniethical.py
brandaniethical/poetry.lock
brandaniethical/pyproject.toml
brandaniethical-0.1.0.dist-info/LICENSE
brandaniethical-0.1.0.dist-info/WHEEL
brandaniethical-0.1.0.dist-info/METADATA
brandaniethical-0.1.0.dist-info/RECORD
