Metadata-Version: 2.1
Name: brandaniethical
Version: 0.1.0
Summary: A package for green consumers and investors to quickly get a view of fashion brands’ animal policy, rate, and animal material usage. and check trendy tickers esg from yahoo finance and esg api
License: MIT
Author: Yang Hu
Requires-Python: >=3.8,<4.0
Classifier: License :: OSI Approved :: MIT License
Classifier: Programming Language :: Python :: 3
Classifier: Programming Language :: Python :: 3.10
Classifier: Programming Language :: Python :: 3.8
Classifier: Programming Language :: Python :: 3.9
Requires-Dist: bs4 (>=0.0.1,<0.0.2)
Requires-Dist: lxml (>=4.7.1,<5.0.0)
Requires-Dist: pandas (>=1.3.5,<2.0.0)
Requires-Dist: pytest (>=6.2.5,<7.0.0)
Requires-Dist: requests (>=2.26.0,<3.0.0)
